optimparameters/.DS_Store
optimparameters/__init__.py
optimparameters/parameters.py
optimparameters/__pycache__/__init__.cpython-37.pyc
optimparameters/__pycache__/parameters.cpython-37.pyc
optimparameters/__pycache__/priors.cpython-37.pyc
optimparameters-1.0.6.dist-info/LICENSE.txt
optimparameters-1.0.6.dist-info/METADATA
optimparameters-1.0.6.dist-info/WHEEL
optimparameters-1.0.6.dist-info/top_level.txt
optimparameters-1.0.6.dist-info/RECORD
