Metadata-Version: 2.1
Name: optimparameters
Version: 1.0.6
Summary: Simple optimization parameters implementation.
Home-page: https://github.com/astrobc1/optimparameters
Author: Bryson Cale
Author-email: bryson.cale1@gmail.com
License: UNKNOWN
Platform: UNKNOWN
Classifier: Programming Language :: Python :: 3
Classifier: Operating System :: Unix
Requires-Python: >=3.6
Requires-Dist: numba (>=0.48)
Requires-Dist: numpy (>=1.18)
